LICENSE.txt
README.md
setup.py
rocket_ayoub_lab3/__init__.py
rocket_ayoub_lab3/rocket.py
rocket_ayoub_lab3.egg-info/PKG-INFO
rocket_ayoub_lab3.egg-info/SOURCES.txt
rocket_ayoub_lab3.egg-info/dependency_links.txt
rocket_ayoub_lab3.egg-info/top_level.txt